{"Save":"שמירה","Video":"וידאו","Add":"הוספה","Game":"משחק","MediaType":"סוג מדיה","ExternalPlayers":"נגנים חיצוניים","ExternalPlayer":"נגן חיצוני","PlayerPath":"נתיב הנגן","ArgumentsHelp":"מקם כל משתנה בשורה נפרדת","TokenPath":"{path} = נתיב לקובץ מדיה","EnableFor":"אפשר עבור:","VideoFiles":"קבצי וידאו","InternetStreams":"זרמי אינטרנט","CommandLineArguments":"משתני שורת פקודה","TokenStartPosMs":"{ms} = נקודת התחלה במילישניות (אלפית השנייה)","AdditionalFilters":"מסננים נוספים:","GameSystem":"קונסולת משחקים:","TokenStartPosSeconds":"{Seconds} = start position seconds"}